[
  {
    "id": "L5-001",
    "level": 5,
    "title": "Dĺžka reťazca",
    "statement": "Na vstupe je text. Vypíš jeho dĺžku.",
    "mode": "solve",
    "starter_code": "s = input()\nprint()\n",
    "hints": [
      "Použi len(s).",
      "Dĺžka reťazca je počet znakov.",
      "Riešenie: print(len(s))"
    ],
    "test_cases": [
      {
        "input": "Ahoj\n",
        "output": "4\n",
        "visible": true
      },
      {
        "input": "\n",
        "output": "0\n",
        "visible": false
      },
      {
        "input": "Python\n",
        "output": "6\n",
        "visible": false
      },
      {
        "input": "a b\n",
        "output": "3\n",
        "visible": false
      }
    ],
    "reference_solution": "s = input()\nprint(len(s))\n",
    "schema_version": 2,
    "checks": {
      "forbiddenPatterns": [
        {
          "pattern": "\\bopen\\s*\\(",
          "message": "V tejto úlohe nepracuj so súbormi."
        },
        {
          "pattern": "\\beval\\s*\\(",
          "message": "Nepoužívaj eval(). Rieš úlohu bežným kódom."
        },
        {
          "pattern": "\\bexec\\s*\\(",
          "message": "Nepoužívaj exec(). Rieš úlohu bežným kódom."
        }
      ]
    },
    "teacher_comment": "Verzia v2: pôvodné tests sú prerobené na test_cases a doplnené o skryté prípady proti hardcodu výstupu."
  },
  {
    "id": "L5-002",
    "level": 5,
    "title": "Prvý a posledný znak",
    "statement": "Na vstupe je neprázdny text. Vypíš prvý a posledný znak na jeden riadok bez medzery (napr. 'aZ').",
    "mode": "solve",
    "starter_code": "s = input()\n# doplň\n",
    "hints": [
      "Prvý znak je s[0].",
      "Posledný znak je s[-1].",
      "Vypíš s[0] + s[-1]."
    ],
    "test_cases": [
      {
        "input": "abc\n",
        "output": "ac\n",
        "visible": true
      },
      {
        "input": "Z\n",
        "output": "ZZ\n",
        "visible": false
      },
      {
        "input": "python\n",
        "output": "pn\n",
        "visible": false
      },
      {
        "input": "ahoj\n",
        "output": "aj\n",
        "visible": false
      }
    ],
    "reference_solution": "s = input()\nprint(s[0] + s[-1])\n",
    "schema_version": 2,
    "checks": {
      "forbiddenPatterns": [
        {
          "pattern": "\\bopen\\s*\\(",
          "message": "V tejto úlohe nepracuj so súbormi."
        },
        {
          "pattern": "\\beval\\s*\\(",
          "message": "Nepoužívaj eval(). Rieš úlohu bežným kódom."
        },
        {
          "pattern": "\\bexec\\s*\\(",
          "message": "Nepoužívaj exec(). Rieš úlohu bežným kódom."
        }
      ]
    },
    "teacher_comment": "Verzia v2: pôvodné tests sú prerobené na test_cases a doplnené o skryté prípady proti hardcodu výstupu."
  },
  {
    "id": "L5-003",
    "level": 5,
    "title": "Počet slov",
    "statement": "Na vstupe je veta. Spočítaj počet slov (oddelené medzerami).",
    "mode": "solve",
    "starter_code": "text = input()\n# doplň\n",
    "hints": [
      "Použi split().",
      "words = text.split()",
      "Počet je len(words)."
    ],
    "test_cases": [
      {
        "input": "Ahoj svet\n",
        "output": "2\n",
        "visible": true
      },
      {
        "input": "Python je super\n",
        "output": "3\n",
        "visible": false
      },
      {
        "input": "  viac   medzier tu  \n",
        "output": "3\n",
        "visible": false
      },
      {
        "input": "jedno\n",
        "output": "1\n",
        "visible": false
      }
    ],
    "reference_solution": "text = input()\nwords = text.split()\nprint(len(words))\n",
    "schema_version": 2,
    "checks": {
      "forbiddenPatterns": [
        {
          "pattern": "\\bopen\\s*\\(",
          "message": "V tejto úlohe nepracuj so súbormi."
        },
        {
          "pattern": "\\beval\\s*\\(",
          "message": "Nepoužívaj eval(). Rieš úlohu bežným kódom."
        },
        {
          "pattern": "\\bexec\\s*\\(",
          "message": "Nepoužívaj exec(). Rieš úlohu bežným kódom."
        }
      ]
    },
    "teacher_comment": "Verzia v2: pôvodné tests sú prerobené na test_cases a doplnené o skryté prípady proti hardcodu výstupu."
  },
  {
    "id": "L5-004",
    "level": 5,
    "title": "Reverz slov",
    "statement": "Na vstupe je veta. Vypíš slová v opačnom poradí, oddelené jednou medzerou.",
    "mode": "solve",
    "starter_code": "text = input()\n# doplň\n",
    "hints": [
      "Rozdeľ: words = text.split()",
      "Otoč: words[::-1]",
      "Spoj: ' '.join(...)"
    ],
    "test_cases": [
      {
        "input": "Ahoj svet\n",
        "output": "svet Ahoj\n",
        "visible": true
      },
      {
        "input": "ja mam rad python\n",
        "output": "python rad mam ja\n",
        "visible": false
      },
      {
        "input": "jedno\n",
        "output": "jedno\n",
        "visible": false
      },
      {
        "input": "a b c d\n",
        "output": "d c b a\n",
        "visible": false
      }
    ],
    "reference_solution": "text = input()\nwords = text.split()\nprint(' '.join(words[::-1]))\n",
    "schema_version": 2,
    "checks": {
      "forbiddenPatterns": [
        {
          "pattern": "\\bopen\\s*\\(",
          "message": "V tejto úlohe nepracuj so súbormi."
        },
        {
          "pattern": "\\beval\\s*\\(",
          "message": "Nepoužívaj eval(). Rieš úlohu bežným kódom."
        },
        {
          "pattern": "\\bexec\\s*\\(",
          "message": "Nepoužívaj exec(). Rieš úlohu bežným kódom."
        }
      ]
    },
    "teacher_comment": "Verzia v2: pôvodné tests sú prerobené na test_cases a doplnené o skryté prípady proti hardcodu výstupu."
  },
  {
    "id": "L5-F01",
    "level": 5,
    "title": "Fix: join naopak",
    "statement": "Kód má spojiť slová pomlčkami, ale dáva zlý výsledok. Oprav ho.",
    "mode": "fix",
    "starter_code": "",
    "buggy_solutions": [
      {
        "id": "B1",
        "title": "Použije split('-') namiesto join('-')",
        "misconceptionTag": "split_join_confusion",
        "code": "text = input()\nwords = text.split()\nprint(words.split('-'))\n"
      },
      {
        "id": "B2",
        "title": "Vypíše list, nie text",
        "misconceptionTag": "printing_list",
        "code": "text = input()\nwords = text.split()\nprint(words)\n"
      }
    ],
    "hints": [
      "split() robí zo stringu list.",
      "join() robí z listu string.",
      "Použi: print('-'.join(words))"
    ],
    "test_cases": [
      {
        "input": "a b c\n",
        "output": "a-b-c\n",
        "visible": true
      },
      {
        "input": "Python je super\n",
        "output": "Python-je-super\n",
        "visible": false
      },
      {
        "input": "jeden dva\n",
        "output": "jeden-dva\n",
        "visible": false
      },
      {
        "input": "solo\n",
        "output": "solo\n",
        "visible": false
      }
    ],
    "reference_solution": "text = input()\nwords = text.split()\nprint('-'.join(words))\n",
    "schema_version": 2,
    "checks": {
      "forbiddenPatterns": [
        {
          "pattern": "\\bopen\\s*\\(",
          "message": "V tejto úlohe nepracuj so súbormi."
        },
        {
          "pattern": "\\beval\\s*\\(",
          "message": "Nepoužívaj eval(). Rieš úlohu bežným kódom."
        },
        {
          "pattern": "\\bexec\\s*\\(",
          "message": "Nepoužívaj exec(). Rieš úlohu bežným kódom."
        }
      ]
    },
    "teacher_comment": "Verzia v2: pôvodné tests sú prerobené na test_cases a doplnené o skryté prípady proti hardcodu výstupu."
  },
  {
    "id": "L5-P01",
    "level": 5,
    "title": "Predict: slicing",
    "statement": "Tipni výstup a potom Run.",
    "mode": "predict",
    "starter_code": "s = 'abcdef'\nprint(s[1:4])\n",
    "hints": [
      "Slicing s[a:b] berie a..b-1.",
      "Indexy 1,2,3 sú b,c,d.",
      "Výstup je bcd."
    ],
    "test_cases": [
      {
        "input": "",
        "output": "bcd\n",
        "visible": true
      }
    ],
    "schema_version": 2,
    "checks": {
      "forbiddenPatterns": [
        {
          "pattern": "\\bopen\\s*\\(",
          "message": "V tejto úlohe nepracuj so súbormi."
        },
        {
          "pattern": "\\beval\\s*\\(",
          "message": "Nepoužívaj eval(). Rieš úlohu bežným kódom."
        },
        {
          "pattern": "\\bexec\\s*\\(",
          "message": "Nepoužívaj exec(). Rieš úlohu bežným kódom."
        }
      ]
    },
    "teacher_comment": "Predict úloha: test_cases slúžia na overenie očakávaného výstupu po spustení, nie na viacvstupové testovanie."
  },
  {
    "id": "L5-005",
    "level": 5,
    "title": "Druhý znak",
    "statement": "Na vstupe je text s dĺžkou aspoň 2. Vypíš jeho druhý znak.",
    "mode": "solve",
    "starter_code": "text = input()\nprint()\n",
    "hints": [
      "Indexovanie začína od 0.",
      "Druhý znak má index 1.",
      "Riešenie: print(text[1])"
    ],
    "concepts": [
      "indexing",
      "string"
    ],
    "difficulty": 1,
    "teacher_comment": "Verzia v2: pôvodné tests sú prerobené na test_cases a doplnené o skryté prípady proti hardcodu výstupu.",
    "test_cases": [
      {
        "input": "python\n",
        "output": "y\n",
        "visible": true
      },
      {
        "input": "ab\n",
        "output": "b\n",
        "visible": false
      },
      {
        "input": "xy\n",
        "output": "y\n",
        "visible": false
      },
      {
        "input": "Ahoj\n",
        "output": "h\n",
        "visible": false
      }
    ],
    "reference_solution": "text = input()\nprint(text[1])\n",
    "schema_version": 2,
    "checks": {
      "forbiddenPatterns": [
        {
          "pattern": "\\bopen\\s*\\(",
          "message": "V tejto úlohe nepracuj so súbormi."
        },
        {
          "pattern": "\\beval\\s*\\(",
          "message": "Nepoužívaj eval(). Rieš úlohu bežným kódom."
        },
        {
          "pattern": "\\bexec\\s*\\(",
          "message": "Nepoužívaj exec(). Rieš úlohu bežným kódom."
        }
      ]
    }
  },
  {
    "id": "L5-006",
    "level": 5,
    "title": "Bez prvého znaku",
    "statement": "Na vstupe je text. Vypíš text bez prvého znaku.",
    "mode": "solve",
    "starter_code": "text = input()\nprint()\n",
    "hints": [
      "Použi slicing od indexu 1.",
      "text[1:] znamená od druhého znaku po koniec.",
      "Riešenie: print(text[1:])"
    ],
    "concepts": [
      "slicing"
    ],
    "difficulty": 2,
    "teacher_comment": "Verzia v2: pôvodné tests sú prerobené na test_cases a doplnené o skryté prípady proti hardcodu výstupu.",
    "test_cases": [
      {
        "input": "python\n",
        "output": "ython\n",
        "visible": true
      },
      {
        "input": "Ahoj\n",
        "output": "hoj\n",
        "visible": false
      },
      {
        "input": "x\n",
        "output": "\n",
        "visible": false
      },
      {
        "input": "test\n",
        "output": "est\n",
        "visible": false
      }
    ],
    "reference_solution": "text = input()\nprint(text[1:])\n",
    "schema_version": 2,
    "checks": {
      "forbiddenPatterns": [
        {
          "pattern": "\\bopen\\s*\\(",
          "message": "V tejto úlohe nepracuj so súbormi."
        },
        {
          "pattern": "\\beval\\s*\\(",
          "message": "Nepoužívaj eval(). Rieš úlohu bežným kódom."
        },
        {
          "pattern": "\\bexec\\s*\\(",
          "message": "Nepoužívaj exec(). Rieš úlohu bežným kódom."
        }
      ]
    }
  },
  {
    "id": "L5-007",
    "level": 5,
    "title": "Prvé tri znaky",
    "statement": "Na vstupe je text. Vypíš jeho prvé tri znaky.",
    "mode": "solve",
    "starter_code": "text = input()\nprint()\n",
    "hints": [
      "Horná hranica slicingu sa nezahŕňa.",
      "Prvé tri znaky sú text[:3].",
      "Riešenie: print(text[:3])"
    ],
    "concepts": [
      "slicing"
    ],
    "difficulty": 2,
    "teacher_comment": "Verzia v2: pôvodné tests sú prerobené na test_cases a doplnené o skryté prípady proti hardcodu výstupu.",
    "test_cases": [
      {
        "input": "program\n",
        "output": "pro\n",
        "visible": true
      },
      {
        "input": "abcde\n",
        "output": "abc\n",
        "visible": false
      },
      {
        "input": "xy\n",
        "output": "xy\n",
        "visible": false
      },
      {
        "input": "abcdef\n",
        "output": "abc\n",
        "visible": false
      }
    ],
    "reference_solution": "text = input()\nprint(text[:3])\n",
    "schema_version": 2,
    "checks": {
      "forbiddenPatterns": [
        {
          "pattern": "\\bopen\\s*\\(",
          "message": "V tejto úlohe nepracuj so súbormi."
        },
        {
          "pattern": "\\beval\\s*\\(",
          "message": "Nepoužívaj eval(). Rieš úlohu bežným kódom."
        },
        {
          "pattern": "\\bexec\\s*\\(",
          "message": "Nepoužívaj exec(). Rieš úlohu bežným kódom."
        }
      ]
    }
  },
  {
    "id": "L5-008",
    "level": 5,
    "title": "Každý druhý znak",
    "statement": "Na vstupe je text. Vypíš každý druhý znak od začiatku.",
    "mode": "solve",
    "starter_code": "text = input()\nprint()\n",
    "hints": [
      "Slicing má tvar start:end:krok.",
      "Krok 2 vyberie každý druhý znak.",
      "Riešenie: print(text[::2])"
    ],
    "concepts": [
      "slicing step"
    ],
    "difficulty": 3,
    "teacher_comment": "Verzia v2: pôvodné tests sú prerobené na test_cases a doplnené o skryté prípady proti hardcodu výstupu.",
    "test_cases": [
      {
        "input": "abcdef\n",
        "output": "ace\n",
        "visible": true
      },
      {
        "input": "python\n",
        "output": "pto\n",
        "visible": false
      },
      {
        "input": "a\n",
        "output": "a\n",
        "visible": false
      },
      {
        "input": "1234567\n",
        "output": "1357\n",
        "visible": false
      }
    ],
    "reference_solution": "text = input()\nprint(text[::2])\n",
    "schema_version": 2,
    "checks": {
      "forbiddenPatterns": [
        {
          "pattern": "\\bopen\\s*\\(",
          "message": "V tejto úlohe nepracuj so súbormi."
        },
        {
          "pattern": "\\beval\\s*\\(",
          "message": "Nepoužívaj eval(). Rieš úlohu bežným kódom."
        },
        {
          "pattern": "\\bexec\\s*\\(",
          "message": "Nepoužívaj exec(). Rieš úlohu bežným kódom."
        }
      ]
    }
  },
  {
    "id": "L5-009",
    "level": 5,
    "title": "Otoč text",
    "statement": "Na vstupe je text. Vypíš ho odzadu.",
    "mode": "solve",
    "starter_code": "text = input()\nprint()\n",
    "hints": [
      "Slicing s krokom -1 otočí text.",
      "Použi text[::-1].",
      "Riešenie: print(text[::-1])"
    ],
    "concepts": [
      "slicing negative step"
    ],
    "difficulty": 3,
    "teacher_comment": "Verzia v2: pôvodné tests sú prerobené na test_cases a doplnené o skryté prípady proti hardcodu výstupu.",
    "test_cases": [
      {
        "input": "abc\n",
        "output": "cba\n",
        "visible": true
      },
      {
        "input": "ahoj\n",
        "output": "joha\n",
        "visible": false
      },
      {
        "input": "Python\n",
        "output": "nohtyP\n",
        "visible": false
      },
      {
        "input": "a\n",
        "output": "a\n",
        "visible": false
      }
    ],
    "reference_solution": "text = input()\nprint(text[::-1])\n",
    "schema_version": 2,
    "checks": {
      "forbiddenPatterns": [
        {
          "pattern": "\\bopen\\s*\\(",
          "message": "V tejto úlohe nepracuj so súbormi."
        },
        {
          "pattern": "\\beval\\s*\\(",
          "message": "Nepoužívaj eval(). Rieš úlohu bežným kódom."
        },
        {
          "pattern": "\\bexec\\s*\\(",
          "message": "Nepoužívaj exec(). Rieš úlohu bežným kódom."
        }
      ]
    }
  },
  {
    "id": "L5-010",
    "level": 5,
    "title": "Slová na riadkoch",
    "statement": "Na vstupe je veta. Vypíš každé slovo na samostatný riadok.",
    "mode": "solve",
    "starter_code": "veta = input()\nslova = veta.split()\n",
    "hints": [
      "split() rozdelí vetu na slová.",
      "Prejdi zoznam slov cyklom.",
      "Každé slovo vypíš."
    ],
    "concepts": [
      "split",
      "for list"
    ],
    "difficulty": 2,
    "teacher_comment": "Verzia v2: pôvodné tests sú prerobené na test_cases a doplnené o skryté prípady proti hardcodu výstupu.",
    "test_cases": [
      {
        "input": "Ahoj svet Python\n",
        "output": "Ahoj\nsvet\nPython\n",
        "visible": true
      },
      {
        "input": "jedno\n",
        "output": "jedno\n",
        "visible": false
      },
      {
        "input": "a b\n",
        "output": "a\nb\n",
        "visible": false
      }
    ],
    "reference_solution": "veta = input()\nslova = veta.split()\nfor slovo in slova:\n    print(slovo)\n",
    "schema_version": 2,
    "checks": {
      "forbiddenPatterns": [
        {
          "pattern": "\\bopen\\s*\\(",
          "message": "V tejto úlohe nepracuj so súbormi."
        },
        {
          "pattern": "\\beval\\s*\\(",
          "message": "Nepoužívaj eval(). Rieš úlohu bežným kódom."
        },
        {
          "pattern": "\\bexec\\s*\\(",
          "message": "Nepoužívaj exec(). Rieš úlohu bežným kódom."
        }
      ]
    }
  },
  {
    "id": "L5-011",
    "level": 5,
    "title": "Prvé slovo",
    "statement": "Na vstupe je veta aspoň s jedným slovom. Vypíš prvé slovo.",
    "mode": "solve",
    "starter_code": "veta = input()\nslova = veta.split()\nprint()\n",
    "hints": [
      "split() vráti zoznam slov.",
      "Prvý prvok má index 0.",
      "Riešenie: print(slova[0])"
    ],
    "concepts": [
      "split",
      "list indexing"
    ],
    "difficulty": 2,
    "teacher_comment": "Verzia v2: pôvodné tests sú prerobené na test_cases a doplnené o skryté prípady proti hardcodu výstupu.",
    "test_cases": [
      {
        "input": "dobré ráno trieda\n",
        "output": "dobré\n",
        "visible": true
      },
      {
        "input": "Python\n",
        "output": "Python\n",
        "visible": false
      },
      {
        "input": "  prve druhe  \n",
        "output": "prve\n",
        "visible": false
      }
    ],
    "reference_solution": "veta = input()\nslova = veta.split()\nprint(slova[0])\n",
    "schema_version": 2,
    "checks": {
      "forbiddenPatterns": [
        {
          "pattern": "\\bopen\\s*\\(",
          "message": "V tejto úlohe nepracuj so súbormi."
        },
        {
          "pattern": "\\beval\\s*\\(",
          "message": "Nepoužívaj eval(). Rieš úlohu bežným kódom."
        },
        {
          "pattern": "\\bexec\\s*\\(",
          "message": "Nepoužívaj exec(). Rieš úlohu bežným kódom."
        }
      ]
    }
  },
  {
    "id": "L5-012",
    "level": 5,
    "title": "Posledné slovo",
    "statement": "Na vstupe je veta. Vypíš posledné slovo.",
    "mode": "solve",
    "starter_code": "veta = input()\nslova = veta.split()\nprint()\n",
    "hints": [
      "Posledný prvok má index -1.",
      "Použi slova[-1].",
      "Riešenie: print(slova[-1])"
    ],
    "concepts": [
      "negative index",
      "split"
    ],
    "difficulty": 2,
    "teacher_comment": "Verzia v2: pôvodné tests sú prerobené na test_cases a doplnené o skryté prípady proti hardcodu výstupu.",
    "test_cases": [
      {
        "input": "dnes sa učíme Python\n",
        "output": "Python\n",
        "visible": true
      },
      {
        "input": "ahoj\n",
        "output": "ahoj\n",
        "visible": false
      },
      {
        "input": "prve druhe tretie\n",
        "output": "tretie\n",
        "visible": false
      }
    ],
    "reference_solution": "veta = input()\nslova = veta.split()\nprint(slova[-1])\n",
    "schema_version": 2,
    "checks": {
      "forbiddenPatterns": [
        {
          "pattern": "\\bopen\\s*\\(",
          "message": "V tejto úlohe nepracuj so súbormi."
        },
        {
          "pattern": "\\beval\\s*\\(",
          "message": "Nepoužívaj eval(). Rieš úlohu bežným kódom."
        },
        {
          "pattern": "\\bexec\\s*\\(",
          "message": "Nepoužívaj exec(). Rieš úlohu bežným kódom."
        }
      ]
    }
  },
  {
    "id": "L5-013",
    "level": 5,
    "title": "Spoj slov pomlčkou",
    "statement": "Na vstupe je veta. Vypíš jej slová spojené pomlčkou.",
    "mode": "solve",
    "starter_code": "veta = input()\nslova = veta.split()\nprint()\n",
    "hints": [
      "split() vytvorí zoznam.",
      "\"-\".join(slova) spojí zoznam pomlčkou.",
      "Pozor: join voláme na oddeľovači."
    ],
    "concepts": [
      "split",
      "join"
    ],
    "difficulty": 3,
    "teacher_comment": "Verzia v2: pôvodné tests sú prerobené na test_cases a doplnené o skryté prípady proti hardcodu výstupu.",
    "test_cases": [
      {
        "input": "a b c\n",
        "output": "a-b-c\n",
        "visible": true
      },
      {
        "input": "Python je super\n",
        "output": "Python-je-super\n",
        "visible": false
      },
      {
        "input": "jedno\n",
        "output": "jedno\n",
        "visible": false
      },
      {
        "input": "  a   b  c \n",
        "output": "a-b-c\n",
        "visible": false
      }
    ],
    "reference_solution": "veta = input()\nslova = veta.split()\nprint('-'.join(slova))\n",
    "schema_version": 2,
    "checks": {
      "forbiddenPatterns": [
        {
          "pattern": "\\bopen\\s*\\(",
          "message": "V tejto úlohe nepracuj so súbormi."
        },
        {
          "pattern": "\\beval\\s*\\(",
          "message": "Nepoužívaj eval(). Rieš úlohu bežným kódom."
        },
        {
          "pattern": "\\bexec\\s*\\(",
          "message": "Nepoužívaj exec(). Rieš úlohu bežným kódom."
        }
      ]
    }
  },
  {
    "id": "L5-014",
    "level": 5,
    "title": "Zoznam čísel: súčet",
    "statement": "Na vstupe je jeden riadok s celými číslami oddelenými medzerou. Vypíš ich súčet.",
    "mode": "solve",
    "starter_code": "riadok = input()\ncasti = riadok.split()\ns = 0\n",
    "hints": [
      "split() dá textové časti.",
      "Každú časť treba previesť cez int().",
      "Pridávaj do súčtu."
    ],
    "concepts": [
      "split",
      "int conversion",
      "accumulator"
    ],
    "difficulty": 3,
    "teacher_comment": "Verzia v2: pôvodné tests sú prerobené na test_cases a doplnené o skryté prípady proti hardcodu výstupu.",
    "test_cases": [
      {
        "input": "1 2 3 4\n",
        "output": "10\n",
        "visible": true
      },
      {
        "input": "-1 5 0\n",
        "output": "4\n",
        "visible": false
      },
      {
        "input": "0 0 0\n",
        "output": "0\n",
        "visible": false
      },
      {
        "input": "10 -3 2\n",
        "output": "9\n",
        "visible": false
      }
    ],
    "reference_solution": "riadok = input()\ncasti = riadok.split()\ns = 0\nfor cast in casti:\n    s += int(cast)\nprint(s)\n",
    "schema_version": 2,
    "checks": {
      "forbiddenPatterns": [
        {
          "pattern": "\\bopen\\s*\\(",
          "message": "V tejto úlohe nepracuj so súbormi."
        },
        {
          "pattern": "\\beval\\s*\\(",
          "message": "Nepoužívaj eval(). Rieš úlohu bežným kódom."
        },
        {
          "pattern": "\\bexec\\s*\\(",
          "message": "Nepoužívaj exec(). Rieš úlohu bežným kódom."
        }
      ]
    }
  },
  {
    "id": "L5-015",
    "level": 5,
    "title": "Zoznam čísel: maximum",
    "statement": "Na vstupe je jeden riadok s celými číslami oddelenými medzerou. Vypíš najväčšie číslo.",
    "mode": "solve",
    "starter_code": "cisla = input().split()\n",
    "hints": [
      "Textové hodnoty treba meniť na int.",
      "Môžeš použiť cyklus a maximum.",
      "Alebo max(map(int, cisla))."
    ],
    "concepts": [
      "split",
      "maximum"
    ],
    "difficulty": 3,
    "teacher_comment": "Verzia v2: pôvodné tests sú prerobené na test_cases a doplnené o skryté prípady proti hardcodu výstupu.",
    "test_cases": [
      {
        "input": "3 9 2 5\n",
        "output": "9\n",
        "visible": true
      },
      {
        "input": "-5 -2 -9\n",
        "output": "-2\n",
        "visible": false
      },
      {
        "input": "1\n",
        "output": "1\n",
        "visible": false
      },
      {
        "input": "100 20 3\n",
        "output": "100\n",
        "visible": false
      }
    ],
    "reference_solution": "cisla = input().split()\nnaj = int(cisla[0])\nfor c in cisla:\n    x = int(c)\n    if x > naj:\n        naj = x\nprint(naj)\n",
    "schema_version": 2,
    "checks": {
      "forbiddenPatterns": [
        {
          "pattern": "\\bopen\\s*\\(",
          "message": "V tejto úlohe nepracuj so súbormi."
        },
        {
          "pattern": "\\beval\\s*\\(",
          "message": "Nepoužívaj eval(). Rieš úlohu bežným kódom."
        },
        {
          "pattern": "\\bexec\\s*\\(",
          "message": "Nepoužívaj exec(). Rieš úlohu bežným kódom."
        }
      ]
    }
  },
  {
    "id": "L5-016",
    "level": 5,
    "title": "Vymeň prvý a posledný prvok",
    "statement": "Na vstupe je riadok so slovami. Vymeň prvé a posledné slovo a vypíš celý zoznam slov spojený medzerami.",
    "mode": "solve",
    "starter_code": "slova = input().split()\n",
    "hints": [
      "Prvý index je 0, posledný -1.",
      "Výmena: slova[0], slova[-1] = slova[-1], slova[0].",
      "Na výpis použi \" \".join(slova)."
    ],
    "concepts": [
      "list mutation",
      "join"
    ],
    "difficulty": 4,
    "teacher_comment": "Verzia v2: pôvodné tests sú prerobené na test_cases a doplnené o skryté prípady proti hardcodu výstupu.",
    "test_cases": [
      {
        "input": "jeden dva tri\n",
        "output": "tri dva jeden\n",
        "visible": true
      },
      {
        "input": "A B\n",
        "output": "B A\n",
        "visible": false
      },
      {
        "input": "solo\n",
        "output": "solo\n",
        "visible": false
      },
      {
        "input": "a b c d\n",
        "output": "d b c a\n",
        "visible": false
      }
    ],
    "reference_solution": "slova = input().split()\nif len(slova) > 1:\n    slova[0], slova[-1] = slova[-1], slova[0]\nprint(' '.join(slova))\n",
    "schema_version": 2,
    "checks": {
      "forbiddenPatterns": [
        {
          "pattern": "\\bopen\\s*\\(",
          "message": "V tejto úlohe nepracuj so súbormi."
        },
        {
          "pattern": "\\beval\\s*\\(",
          "message": "Nepoužívaj eval(). Rieš úlohu bežným kódom."
        },
        {
          "pattern": "\\bexec\\s*\\(",
          "message": "Nepoužívaj exec(). Rieš úlohu bežným kódom."
        }
      ]
    }
  },
  {
    "id": "L5-017",
    "level": 5,
    "title": "Pridaj slovo na koniec",
    "statement": "Na vstupe je veta a potom nové slovo. Pridaj slovo na koniec a vypíš vetu.",
    "mode": "solve",
    "starter_code": "slova = input().split()\nnové = input()\n",
    "hints": [
      "append pridá prvok na koniec zoznamu.",
      "Potom zoznam spoj medzerou.",
      "slova.append(nové)"
    ],
    "concepts": [
      "list append",
      "join"
    ],
    "difficulty": 2,
    "teacher_comment": "Verzia v2: pôvodné tests sú prerobené na test_cases a doplnené o skryté prípady proti hardcodu výstupu.",
    "test_cases": [
      {
        "input": "učíme sa\nPython\n",
        "output": "učíme sa Python\n",
        "visible": true
      },
      {
        "input": "a b\nc\n",
        "output": "a b c\n",
        "visible": false
      },
      {
        "input": "jedno\ndruhe\n",
        "output": "jedno druhe\n",
        "visible": false
      }
    ],
    "reference_solution": "slova = input().split()\nnové = input()\nslova.append(nové)\nprint(' '.join(slova))\n",
    "schema_version": 2,
    "checks": {
      "forbiddenPatterns": [
        {
          "pattern": "\\bopen\\s*\\(",
          "message": "V tejto úlohe nepracuj so súbormi."
        },
        {
          "pattern": "\\beval\\s*\\(",
          "message": "Nepoužívaj eval(). Rieš úlohu bežným kódom."
        },
        {
          "pattern": "\\bexec\\s*\\(",
          "message": "Nepoužívaj exec(). Rieš úlohu bežným kódom."
        }
      ]
    }
  },
  {
    "id": "L5-018",
    "level": 5,
    "title": "Odstráň prvé slovo",
    "statement": "Na vstupe je veta aspoň s dvomi slovami. Odstráň prvé slovo a zvyšok vypíš ako vetu.",
    "mode": "solve",
    "starter_code": "slova = input().split()\n",
    "hints": [
      "Môžeš použiť slicing slova[1:].",
      "Potom spoj pomocou \" \".join().",
      "Nemeň znaky, ale slová."
    ],
    "concepts": [
      "list slicing",
      "join"
    ],
    "difficulty": 3,
    "teacher_comment": "Verzia v2: pôvodné tests sú prerobené na test_cases a doplnené o skryté prípady proti hardcodu výstupu.",
    "test_cases": [
      {
        "input": "toto odstráň\n",
        "output": "odstráň\n",
        "visible": true
      },
      {
        "input": "A B C\n",
        "output": "B C\n",
        "visible": false
      },
      {
        "input": "prve druhe tretie\n",
        "output": "druhe tretie\n",
        "visible": false
      }
    ],
    "reference_solution": "slova = input().split()\nslova.pop(0)\nprint(' '.join(slova))\n",
    "schema_version": 2,
    "checks": {
      "forbiddenPatterns": [
        {
          "pattern": "\\bopen\\s*\\(",
          "message": "V tejto úlohe nepracuj so súbormi."
        },
        {
          "pattern": "\\beval\\s*\\(",
          "message": "Nepoužívaj eval(). Rieš úlohu bežným kódom."
        },
        {
          "pattern": "\\bexec\\s*\\(",
          "message": "Nepoužívaj exec(). Rieš úlohu bežným kódom."
        }
      ]
    }
  },
  {
    "id": "L5-019",
    "level": 5,
    "title": "Len dlhé slová",
    "statement": "Na vstupe je veta. Vypíš iba slová dlhšie ako 3 znaky, každé na vlastnom riadku.",
    "mode": "solve",
    "starter_code": "slova = input().split()\n",
    "hints": [
      "Prejdi zoznam slov.",
      "Dĺžku zistíš cez len(slovo).",
      "Podmienka je len(slovo) > 3."
    ],
    "concepts": [
      "split",
      "filter",
      "len"
    ],
    "difficulty": 3,
    "teacher_comment": "Verzia v2: pôvodné tests sú prerobené na test_cases a doplnené o skryté prípady proti hardcodu výstupu.",
    "test_cases": [
      {
        "input": "ja mam rad python\n",
        "output": "python\n",
        "visible": true
      },
      {
        "input": "toto je test\n",
        "output": "toto\ntest\n",
        "visible": false
      },
      {
        "input": "abcd abc abcde\n",
        "output": "abcd\nabcde\n",
        "visible": false
      },
      {
        "input": "a bb ccc\n",
        "output": "",
        "visible": false
      }
    ],
    "reference_solution": "slova = input().split()\nfor slovo in slova:\n    if len(slovo) > 3:\n        print(slovo)\n",
    "schema_version": 2,
    "checks": {
      "forbiddenPatterns": [
        {
          "pattern": "\\bopen\\s*\\(",
          "message": "V tejto úlohe nepracuj so súbormi."
        },
        {
          "pattern": "\\beval\\s*\\(",
          "message": "Nepoužívaj eval(). Rieš úlohu bežným kódom."
        },
        {
          "pattern": "\\bexec\\s*\\(",
          "message": "Nepoužívaj exec(). Rieš úlohu bežným kódom."
        }
      ]
    }
  },
  {
    "id": "L5-F02",
    "level": 5,
    "title": "Fix: max textov namiesto čísel",
    "statement": "Kód má nájsť najväčšie číslo v riadku, ale porovnáva texty. Oprav ho.",
    "mode": "fix",
    "starter_code": "",
    "buggy_solutions": [
      {
        "id": "B1",
        "title": "Neprevádza na int",
        "misconceptionTag": "string_vs_number_order",
        "code": "casti = input().split()\nprint(max(casti))\n"
      }
    ],
    "hints": [
      "split() dá reťazce.",
      "Reťazce sa porovnávajú lexikograficky.",
      "Preveď prvky na int."
    ],
    "concepts": [
      "debugging",
      "type conversion"
    ],
    "difficulty": 4,
    "teacher_comment": "Verzia v2: pôvodné tests sú prerobené na test_cases a doplnené o skryté prípady proti hardcodu výstupu.",
    "test_cases": [
      {
        "input": "3 20 100\n",
        "output": "100\n",
        "visible": true
      },
      {
        "input": "9 10\n",
        "output": "10\n",
        "visible": false
      },
      {
        "input": "-5 -2 -9\n",
        "output": "-2\n",
        "visible": false
      },
      {
        "input": "100 20 3\n",
        "output": "100\n",
        "visible": false
      }
    ],
    "reference_solution": "casti = input().split()\ncisla = [int(c) for c in casti]\nprint(max(cisla))\n",
    "schema_version": 2,
    "checks": {
      "forbiddenPatterns": [
        {
          "pattern": "\\bopen\\s*\\(",
          "message": "V tejto úlohe nepracuj so súbormi."
        },
        {
          "pattern": "\\beval\\s*\\(",
          "message": "Nepoužívaj eval(). Rieš úlohu bežným kódom."
        },
        {
          "pattern": "\\bexec\\s*\\(",
          "message": "Nepoužívaj exec(). Rieš úlohu bežným kódom."
        }
      ]
    }
  },
  {
    "id": "L5-F03",
    "level": 5,
    "title": "Fix: nemožno meniť znak reťazca",
    "statement": "Kód má zmeniť prvý znak textu na X a vypísať výsledok, ale reťazce sú nemenné. Oprav ho.",
    "mode": "fix",
    "starter_code": "",
    "buggy_solutions": [
      {
        "id": "B1",
        "title": "Pokúša sa meniť reťazec cez index",
        "misconceptionTag": "string_immutable",
        "code": "text = input()\ntext[0] = 'X'\nprint(text)\n"
      }
    ],
    "hints": [
      "Reťazec nemožno meniť priamo cez index.",
      "Vytvor nový reťazec: \"X\" + text[1:].",
      "Potom ho vypíš."
    ],
    "concepts": [
      "debugging",
      "immutability",
      "slicing"
    ],
    "difficulty": 4,
    "teacher_comment": "Verzia v2: pôvodné tests sú prerobené na test_cases a doplnené o skryté prípady proti hardcodu výstupu.",
    "test_cases": [
      {
        "input": "python\n",
        "output": "Xython\n",
        "visible": true
      },
      {
        "input": "ahoj\n",
        "output": "Xhoj\n",
        "visible": false
      },
      {
        "input": "A\n",
        "output": "X\n",
        "visible": false
      },
      {
        "input": "slovo\n",
        "output": "Xlovo\n",
        "visible": false
      }
    ],
    "reference_solution": "text = input()\nprint('X' + text[1:])\n",
    "schema_version": 2,
    "checks": {
      "forbiddenPatterns": [
        {
          "pattern": "\\bopen\\s*\\(",
          "message": "V tejto úlohe nepracuj so súbormi."
        },
        {
          "pattern": "\\beval\\s*\\(",
          "message": "Nepoužívaj eval(). Rieš úlohu bežným kódom."
        },
        {
          "pattern": "\\bexec\\s*\\(",
          "message": "Nepoužívaj exec(). Rieš úlohu bežným kódom."
        }
      ]
    }
  },
  {
    "id": "L5-P02",
    "level": 5,
    "title": "Predict: indexy",
    "statement": "Najprv tipni presný výstup programu. Potom uzamkni odhad a klikni Run.",
    "mode": "predict",
    "starter_code": "text = \"python\"\nprint(text[0])\nprint(text[-1])\nprint(text[1:4])\n",
    "hints": [
      "text[0] je prvý znak.",
      "text[-1] je posledný znak.",
      "text[1:4] obsahuje indexy 1,2,3."
    ],
    "concepts": [
      "indexing",
      "slicing",
      "trace"
    ],
    "difficulty": 2,
    "teacher_comment": "Predict úloha: test_cases slúžia na overenie očakávaného výstupu po spustení, nie na viacvstupové testovanie.",
    "test_cases": [
      {
        "input": "",
        "output": "p\nn\nyth\n",
        "visible": true
      }
    ],
    "schema_version": 2,
    "checks": {
      "forbiddenPatterns": [
        {
          "pattern": "\\bopen\\s*\\(",
          "message": "V tejto úlohe nepracuj so súbormi."
        },
        {
          "pattern": "\\beval\\s*\\(",
          "message": "Nepoužívaj eval(). Rieš úlohu bežným kódom."
        },
        {
          "pattern": "\\bexec\\s*\\(",
          "message": "Nepoužívaj exec(). Rieš úlohu bežným kódom."
        }
      ]
    }
  },
  {
    "id": "L5-P03",
    "level": 5,
    "title": "Predict: split a join",
    "statement": "Najprv tipni presný výstup programu. Potom uzamkni odhad a klikni Run.",
    "mode": "predict",
    "starter_code": "slova = \"a b c\".split()\nslova.append(\"d\")\nprint(\"-\".join(slova))\n",
    "hints": [
      "split vytvorí zoznam troch slov.",
      "append pridá d.",
      "join ich spojí pomlčkou."
    ],
    "concepts": [
      "split",
      "append",
      "join"
    ],
    "difficulty": 2,
    "teacher_comment": "Predict úloha: test_cases slúžia na overenie očakávaného výstupu po spustení, nie na viacvstupové testovanie.",
    "test_cases": [
      {
        "input": "",
        "output": "a-b-c-d\n",
        "visible": true
      }
    ],
    "schema_version": 2,
    "checks": {
      "forbiddenPatterns": [
        {
          "pattern": "\\bopen\\s*\\(",
          "message": "V tejto úlohe nepracuj so súbormi."
        },
        {
          "pattern": "\\beval\\s*\\(",
          "message": "Nepoužívaj eval(). Rieš úlohu bežným kódom."
        },
        {
          "pattern": "\\bexec\\s*\\(",
          "message": "Nepoužívaj exec(). Rieš úlohu bežným kódom."
        }
      ]
    }
  }
]